cyberzard/__init__.py
cyberzard/__main__.py
cyberzard/_version.py
cyberzard/chat.py
cyberzard/cli.py
cyberzard/config.py
cyberzard/email_execute.py
cyberzard/evidence.py
cyberzard/legacy_agent.py
cyberzard/n8n_setup.py
cyberzard/remediation.py
cyberzard/reporting.py
cyberzard/tools.py
cyberzard/tui.py
cyberzard/ui.py
cyberzard/updater.py
cyberzard/agent/__init__.py
cyberzard/agent/orchestrator.py
cyberzard/agent_engine/__init__.py
cyberzard/agent_engine/config.py
cyberzard/agent_engine/provider.py
cyberzard/agent_engine/provider_email.py
cyberzard/agent_engine/verify.py
cyberzard/agent_engine/tools/__init__.py
cyberzard/agent_engine/tools/email_scan.py
cyberzard/agent_engine/tools/file_ops.py
cyberzard/agent_engine/tools/server_scan.py
cyberzard/core/__init__.py
cyberzard/core/config.py
cyberzard/core/history.py
cyberzard/core/models.py
cyberzard/mcp/__init__.py
cyberzard/mcp/client.py
cyberzard/mcp/server.py
cyberzard/models/__init__.py
cyberzard/models/registry.py
cyberzard/models/selector.py
cyberzard/scanners/__init__.py
cyberzard/scanners/file_scanner.py
cyberzard/tools/__init__.py
cyberzard/tools/registry.py
cyberzard/tools/schemas.py
cyberzard/tools/unified.py
cyberzard/tui/__init__.py
cyberzard/tui/app.py
cyberzard/tui/legacy.py
cyberzard/tui/widgets/__init__.py
cyberzard/tui/widgets/conversation.py
cyberzard/tui/widgets/tool_output.py
cyberzard/tui/widgets/tool_panel.py
cyberzard-0.1.20.dist-info/licenses/LICENSE
cyberzard-0.1.20.dist-info/METADATA
cyberzard-0.1.20.dist-info/WHEEL
cyberzard-0.1.20.dist-info/entry_points.txt
cyberzard-0.1.20.dist-info/top_level.txt
cyberzard-0.1.20.dist-info/RECORD
