Metadata-Version: 2.4
Name: cyberzard
Version: 0.1.20
Summary: AI-assisted CyberPanel server scanner and remediation CLI
Author: CyberPanel Wizard
License: MIT
Project-URL: Homepage, https://elwizard33.github.io/Cyberzard
Project-URL: Documentation, https://elwizard33.github.io/Cyberzard
Project-URL: Source, https://github.com/elwizard33/Cyberzard
Project-URL: Issues, https://github.com/elwizard33/Cyberzard/issues
Project-URL: Changelog, https://github.com/elwizard33/Cyberzard/blob/main/CHANGELOG.md
Keywords: security,malware,cyberpanel,cli,ai,langchain,incident-response,server-security
Classifier: Development Status :: 4 - Beta
Classifier: Environment :: Console
Classifier: Programming Language :: Python :: 3
Classifier: Programming Language :: Python :: 3.10
Classifier: Programming Language :: Python :: 3.11
Classifier: Programming Language :: Python :: 3.12
Classifier: Programming Language :: Python :: 3.13
Classifier: License :: OSI Approved :: MIT License
Classifier: Intended Audience :: System Administrators
Classifier: Intended Audience :: Developers
Classifier: Topic :: Security
Classifier: Topic :: System :: Systems Administration
Classifier: Operating System :: POSIX :: Linux
Classifier: Typing :: Typed
Requires-Python: >=3.10
License-File: LICENSE
Requires-Dist: typer>=0.12.0
Requires-Dist: rich>=13.0.0
Requires-Dist: psutil>=5.9.0
Requires-Dist: pydantic>=2.0.0
Requires-Dist: requests>=2.31.0
Requires-Dist: httpx>=0.27.0
Requires-Dist: langchain>=0.3.0
Requires-Dist: langgraph>=0.2.0
Requires-Dist: langchain-openai>=0.2.0
Requires-Dist: langchain-community>=0.3.0
Provides-Extra: anthropic
Requires-Dist: anthropic>=0.29.0; extra == "anthropic"
Requires-Dist: langchain-anthropic>=0.2.0; extra == "anthropic"
Provides-Extra: openai
Requires-Dist: openai>=1.0.0; extra == "openai"
Provides-Extra: xai
Requires-Dist: langchain-xai>=0.1.0; extra == "xai"
Provides-Extra: mcp
Requires-Dist: mcp[cli]>=1.25.0; extra == "mcp"
Provides-Extra: tui
Requires-Dist: textual>=0.60.0; extra == "tui"
Provides-Extra: dev
Requires-Dist: pytest>=7.0.0; extra == "dev"
Requires-Dist: mcp[cli]>=1.25.0; extra == "dev"
Requires-Dist: textual>=0.60.0; extra == "dev"
Requires-Dist: build; extra == "dev"
Requires-Dist: twine; extra == "dev"
Provides-Extra: providers
Requires-Dist: langchain-openai>=0.2.0; extra == "providers"
Requires-Dist: langchain-anthropic>=0.2.0; extra == "providers"
Requires-Dist: langchain-xai>=0.1.0; extra == "providers"
Provides-Extra: all
Requires-Dist: anthropic>=0.29.0; extra == "all"
Requires-Dist: langchain-anthropic>=0.2.0; extra == "all"
Requires-Dist: openai>=1.0.0; extra == "all"
Requires-Dist: langchain-xai>=0.1.0; extra == "all"
Requires-Dist: mcp[cli]>=1.25.0; extra == "all"
Requires-Dist: textual>=0.60.0; extra == "all"
Dynamic: license-file
